blog/__init__.py
blog/admin.py
blog/apps.py
blog/helpers.py
blog/models.py
blog/serializers.py
blog/tests.py
blog/urls.py
blog/utils.py
blog/views.py
blog/migrations/0001_initial.py
blog/migrations/0002_article_change_status_on.py
blog/migrations/__init__.py
blog/tests/__init__.py
blog/tests/test_urls.py
task_app/__init__.py
task_app/admin.py
task_app/apps.py
task_app/choices.py
task_app/helpers.py
task_app/models.py
task_app/serializers.py
task_app/task.py
task_app/tests.py
task_app/utils.py
task_app/views.py
task_app/migrations/0001_initial.py
task_app/migrations/0002_alter_taskqueue_date_time.py
task_app/migrations/__init__.py
django_customized_blog_package-1.0.7.dist-info/LICENSE
django_customized_blog_package-1.0.7.dist-info/METADATA
django_customized_blog_package-1.0.7.dist-info/WHEEL
django_customized_blog_package-1.0.7.dist-info/top_level.txt
django_customized_blog_package-1.0.7.dist-info/RECORD
