Metadata-Version: 2.1
Name: django-customized-blog-package
Version: 1.0.7
Summary: This package is based on the blog project. It provides all the functionality required for a blog project
Home-page: https://github.com/AyanNandaGoswami/BlogModule.git
Author: Ayan Nanda Goswami
Author-email: ayan02472@gmail.com
Maintainer: Ayan Nanda Goswami
Maintainer-email: ayan02472@gmail.com
License: MIT
Project-URL: Documentation, https://blog-module-community.herokuapp.com/
Project-URL: Source, https://github.com/AyanNandaGoswami/BlogModule.git
Project-URL: Tracker, https://github.com/AyanNandaGoswami/BlogModule/issues
Keywords: django customized blog package
Platform: UNKNOWN
Classifier: Programming Language :: Python :: 3
Classifier: License :: OSI Approved :: MIT License
Classifier: Operating System :: OS Independent
Requires-Python: >=3
License-File: LICENSE
Requires-Dist: Django
Requires-Dist: django-ckeditor
Requires-Dist: django-taggit
Requires-Dist: djangorestframework
Requires-Dist: Pillow
Requires-Dist: random2
Requires-Dist: colorama
Requires-Dist: django-filter
